README.rst
setup.py
wave_utils/__init__.py
wave_utils/io.py
wave_utils/waves.py
wave_utils.egg-info/PKG-INFO
wave_utils.egg-info/SOURCES.txt
wave_utils.egg-info/dependency_links.txt
wave_utils.egg-info/top_level.txt