Metadata-Version: 1.1
Name: wave-utils
Version: 0.1.1
Summary: Utilities for computing properties of ocean waves
Home-page: https://github.com/ChrisBarker-NOAA/wave_utils
Author: Chris Barker
Author-email: chris.barker@noaa.gov
License: Public Domain
Download-URL: https://github.com/ChrisBarker-NOAA/wave_utils/archive/v0.1.1.tar.gz
Platform: UNKNOWN
Classifier: Development Status :: 4 - Beta
Classifier: License :: Public Domain
Classifier: Intended Audience :: Science/Research
Classifier: Operating System :: OS Independent
Classifier: Programming Language :: Python
Classifier: Topic :: Utilities
Classifier: Topic :: Scientific/Engineering
